.gitignore
CSS & Design Gallery | Design Shack.webloc
CleanSpace | Design Shack.webloc
MANIFEST.in
README
medialog.subskins-configure.zcml
setup.py
docs/HISTORY.txt
docs/INSTALL.txt
docs/LICENSE.GPL
docs/LICENSE.txt
medialog/.DS_Store
medialog/__init__.py
medialog.subskins.egg-info/PKG-INFO
medialog.subskins.egg-info/SOURCES.txt
medialog.subskins.egg-info/dependency_links.txt
medialog.subskins.egg-info/entry_points.txt
medialog.subskins.egg-info/namespace_packages.txt
medialog.subskins.egg-info/not-zip-safe
medialog.subskins.egg-info/requires.txt
medialog.subskins.egg-info/top_level.txt
medialog/subskins/.DS_Store
medialog/subskins/__init__.py
medialog/subskins/configure.zcml
medialog/subskins/exportimport.py
medialog/subskins/profiles.zcml
medialog/subskins/setuphandlers.py
medialog/subskins/skins.zcml
medialog/subskins/tests.py
medialog/subskins/version.txt
medialog/subskins/browser/.DS_Store
medialog/subskins/browser/__init__.py
medialog/subskins/browser/configure.zcml
medialog/subskins/browser/footerportlets.pt
medialog/subskins/browser/globalnavviewlet.pt
medialog/subskins/browser/interfaces.py
medialog/subskins/browser/managefooterportlets.pt
medialog/subskins/browser/subskins_siteactions.pt
medialog/subskins/browser/subskinscolophon.pt
medialog/subskins/browser/subskinsloader.pt
medialog/subskins/browser/viewlet.pt
medialog/subskins/browser/viewlets.py
medialog/subskins/browser/views.py
medialog/subskins/browser/images/README.txt
medialog/subskins/browser/stylesheets/README.txt
medialog/subskins/browser/stylesheets/main.css
medialog/subskins/profiles/.DS_Store
medialog/subskins/profiles/default/actions.xml
medialog/subskins/profiles/default/cssregistry.xml
medialog/subskins/profiles/default/import_steps.xml
medialog/subskins/profiles/default/jsregistry.xml
medialog/subskins/profiles/default/medialog.subskins_various.txt
medialog/subskins/profiles/default/metadata.xml
medialog/subskins/profiles/default/portlets.xml
medialog/subskins/profiles/default/propertiestool.xml
medialog/subskins/profiles/default/skins.xml
medialog/subskins/profiles/default/subskins_choices.xml
medialog/subskins/profiles/default/viewlets.xml
medialog/subskins/profiles/footerportlets/metadata.xml
medialog/subskins/profiles/footerportlets/portlets.xml
medialog/subskins/skins/.DS_Store
