Metadata-Version: 1.0
Name: medialog.subskins
Version: 4.2.3
Summary: An installable theme and theming tool for Plone 4
Home-page: https://github.com/espenmn/medialog.subskins/
Author: Espen Moe-Nilssen
Author-email: espen@medialog.no
License: GPL
Keywords: web zope plone theme theming tool
Platform: UNKNOWN
Classifier: Framework :: Plone
Classifier: Programming Language :: Python
Classifier: Topic :: Software Development :: Libraries :: Python Modules
